mindsight_django/__init__.py
mindsight_django/config.py
mindsight_django/store.py
mindsight_django_hotpath-0.5.dist-info/METADATA
mindsight_django_hotpath-0.5.dist-info/RECORD
mindsight_django_hotpath-0.5.dist-info/WHEEL
mindsight_django_hotpath-0.5.dist-info/top_level.txt
