Metadata-Version: 2.1
Name: mindsight-django-hotpath
Version: 0.5
Summary: Mindsight Collector for Python/Django
Home-page: https://github.com/MindsightCo/mindsight-django-hotpath
Author: UNKNOWN
Author-email: UNKNOWN
License: Apache 2.0
Platform: UNKNOWN
Requires-Dist: requests
Requires-Dist: django
Requires-Dist: pathlib; python_version < "3.4"
